albus/__init__.py
albus/exceptions.py
albus/field.py
albus/model.py
albus/query.py
albus/db/__init__.py
albus/db/base_types.py
albus/db/engine/__init__.py
albus/db/engine/base.py
albus/db/engine/postgres.py
albus/db/engine/sqlite.py
tests/__init__.py
tests/test_alpha.py
tests/test_query.py
tests/db/__init__.py
tests/db/test_sqlite.py
albus-0.0.2.dist-info/LICENSE
albus-0.0.2.dist-info/METADATA
albus-0.0.2.dist-info/WHEEL
albus-0.0.2.dist-info/top_level.txt
albus-0.0.2.dist-info/RECORD
