Metadata-Version: 2.1
Name: albus
Version: 0.0.2
Summary: Small and dummy DB-API 2 data mapper
Home-page: https://github.com/gotnotable/albus
Author: Rafael Pivato
Author-email: rafael@gotnotable.com
License: UNKNOWN
Platform: UNKNOWN
Classifier: Development Status :: 2 - Pre-Alpha
Classifier: Intended Audience :: Developers
Classifier: License :: OSI Approved :: MIT License
Classifier: Operating System :: OS Independent
Classifier: Programming Language :: Python :: 3
Classifier: Topic :: Database
Classifier: Topic :: Software Development :: Libraries
Requires-Python: >=3.6
